experiments/__init__.py
experiments/anneal_real_graph.py
experiments/neural_trigraph_gym.py
experiments/residual_probs.py
experiments/vertice_ordering.py
graphing/__init__.py
graphing/edge_cover.py
graphing/graph.py
graphing/graph_utils.py
graphing/nx_samples.py
graphing/flow/__init__.py
graphing/flow/min_cost_flow_battle.py
graphing/special_graphs/__init__.py
graphing/special_graphs/bipartite/__init__.py
graphing/special_graphs/bipartite/marginal_matching.py
graphing/special_graphs/bipartite/max_wt_matching.py
graphing/special_graphs/bipartite/min_wt_edge_cover.py
graphing/special_graphs/bipartite/rand_graph.py
graphing/special_graphs/directed_graph/__init__.py
graphing/special_graphs/directed_graph/transitive_closure.py
graphing/special_graphs/neural_trigraph/__init__.py
graphing/special_graphs/neural_trigraph/central_vert.py
graphing/special_graphs/neural_trigraph/neural_trigraph.py
graphing/special_graphs/neural_trigraph/path_cover.py
graphing/special_graphs/neural_trigraph/path_set.py
graphing/special_graphs/neural_trigraph/rand_graph.py
graphing/special_graphs/neural_trigraph/toy_graphs.py
graphing/special_graphs/neural_trigraph/marginal_matching/__init__.py
graphing/special_graphs/neural_trigraph/marginal_matching/evolution.py
graphing/special_graphs/neural_trigraph/marginal_matching/marginal_matching1.py
graphing/special_graphs/neural_trigraph/marginal_matching/residual_probs.py
graphing/special_graphs/neural_trigraph/marginal_matching/scoring.py
graphing/special_graphs/neural_trigraph/marginal_matching/anneal/__init__.py
graphing/special_graphs/neural_trigraph/marginal_matching/anneal/evolutor.py
graphing/special_graphs/neural_trigraph/marginal_matching/anneal/simulated_annealing.py
graphing/special_graphs/neurograph/__init__.py
graphing/special_graphs/neurograph/find_path.py
graphing/special_graphs/neurograph/flow_graph.py
graphing/special_graphs/neurograph/neurograph.py
graphing/special_graphs/neurograph/path_cover.py
graphing-0.0.26.dist-info/LICENSE
graphing-0.0.26.dist-info/METADATA
graphing-0.0.26.dist-info/WHEEL
graphing-0.0.26.dist-info/top_level.txt
graphing-0.0.26.dist-info/RECORD
