Metadata-Version: 2.1
Name: graphing
Version: 0.0.26
Summary: Add static script_dir() method to Path
Home-page: https://github.com/ryu577/graphing
Author: Rohit Pandey
Author-email: rohitpandey576@gmail.com
License: MIT
License-File: LICENSE
